tablestore_mcp_server/__init__.py
tablestore_mcp_server/main.py
tablestore_mcp_server/server.py
tablestore_mcp_server/settings.py
tablestore_mcp_server/tablestore_connector.py
tablestore_mcp_server/embedding/__init__.py
tablestore_mcp_server/embedding/provider.py
tablestore_mcp_server/embedding/type.py
tablestore_mcp_server-0.1.3.dist-info/METADATA
tablestore_mcp_server-0.1.3.dist-info/WHEEL
tablestore_mcp_server-0.1.3.dist-info/entry_points.txt
tablestore_mcp_server-0.1.3.dist-info/licenses/LICENSE
tablestore_mcp_server-0.1.3.dist-info/RECORD
