Metadata-Version: 2.4
Name: tablestore-mcp-server
Version: 0.1.3
Summary: MCP server for retrieving context from a tablestore vector database
License-Expression: Apache-2.0
License-File: LICENSE
Requires-Python: <4.0,>=3.10
Requires-Dist: llama-index-embeddings-dashscope<0.4.0,>=0.3.0
Requires-Dist: llama-index-embeddings-huggingface>=0.5.2
Requires-Dist: llama-index-embeddings-instructor>=0.3.0
Requires-Dist: llama-index-vector-stores-tablestore>=0.2.2
Requires-Dist: llama-index>=0.12.24
Requires-Dist: mcp[cli]>=1.4.1
Requires-Dist: pydantic-settings>=2.8.1
Requires-Dist: pydantic>=2.10.6
Requires-Dist: tablestore>=6.1.0
